{
  "id": "bulgarian_daily_max",
  "name": "Bulgarian Method Daily Max",
  "author_source": "Ivan Abadjiev (Bulgarian WL)",
  "cycle_duration": "open (high frequency)",
  "total_sets": "multiple singles",
  "reps": "1",
  "intensity_unit": "RPE",
  "intensity_range": "Daily max (RPE 9-9.5)",
  "avg_time_session": "30",
  "time_per_session_breakdown": "Work up to daily training max (6-10 singles incl. warm-ups)",
  "amrap": "no",
  "timed": "no",
  "emom": "no",
  "train_to_failure": "no (stop at smooth max)",
  "superset_type": "N/A",
  "spec_movement": "squat/bench (high frequency)",
  "autoregulated": "yes",
  "drop_sets": "no",
  "rest_pause": "no",
  "cluster": "no",
  "tempo_spec": "no",
  "wave_sets": "yes (daily waves)",
  "ladder_sets": "no",
  "density_sets": "no",
  "straight_sets": "yes",
  "contrast_sets": "no",
  "total_rep_target": "n/a",
  "deload": "as needed",
  "overview_and_execution": "Train the same lift daily, ramp to a top single at ~RPE 9. If strong, push slightly above. Often do 1-2 back-off sets at ~90%.",
  "example_application": "Daily squats: ramp to a crisp single (405 lb), maybe 2×2 @ 365 lb. Next day, repeat or adjust by feel.",
  "important_notes": "Advanced method requiring excellent recovery. Avoid grinding lifts daily to prevent burnout.",
  "volume_metrics": "~1 top single daily, plus ramp sets"
}