{
  "id": "gironda_8x8",
  "name": "Gironda’s 8×8 Method",
  "author_source": "Vince Gironda",
  "cycle_duration": "3-4 weeks",
  "total_sets": "8",
  "reps": "8",
  "intensity_unit": "N/A",
  "intensity_range": "Light-Moderate (~60-70% 1RM)",
  "avg_time_session": 8,
  "time_per_session_breakdown": "8 sets x ~15s each + 15-20s rest each = 8 min",
  "amrap": "no",
  "timed": "no",
  "emom": "no",
  "train_to_failure": "no (but close on last sets)",
  "superset_type": "N/A",
  "spec_movement": "mostly isolation or stable compound",
  "autoregulated": "no",
  "drop_sets": "no",
  "rest_pause": "no",
  "cluster": "no",
  "tempo_spec": "2-0-2 recommended",
  "wave_sets": "no",
  "ladder_sets": "no",
  "density_sets": "yes (very short rest)",
  "straight_sets": "yes",
  "contrast_sets": "no",
  "total_rep_target": "64 reps",
  "deload": "after cycle",
  "overview_and_execution": "Extremely short rest intervals (15-20s). Use about 60% 1RM for 8 reps, quickly rest, repeat for 8 total sets, chasing a deep burn.",
  "example_application": "Barbell Curl 8×8 @ 40 lb, 15s rest. If you can complete all sets with good form, increase weight next time.",
  "important_notes": "Focus is on muscle density and definition. Very demanding metabolically. Keep strict form.",
  "volume_metrics": "8×8 = 64 reps"
}