 {
    "id": "restpause_3rm_8min",
    "name": "Rest-Pause (3RM Load) ~8 min",
    "author_source": "T-Nation (user anecdote)",
    "cycle_duration": "open",
    "total_sets": "varies",
    "reps": "1-5",
    "intensity_unit": "%",
    "intensity_range": "85-90% 1RM",
    "avg_time_session": 8,
    "time_per_session_breakdown": "2-3 clusters x ~2 min each + ~2 min rest => ~8 min total",
    "amrap": "no",
    "timed": "no",
    "emom": "no",
    "train_to_failure": "yes",
    "superset_type": "N/A",
    "spec_movement": "open",
    "autoregulated": "no",
    "drop_sets": "no",
    "rest_pause": "yes",
    "cluster": "no",
    "tempo_spec": "no",
    "wave_sets": "no",
    "ladder_sets": "n/a",
    "density_sets": "no",
    "straight_sets": "no",
    "contrast_sets": "no",
    "total_rep_target": "n/a",
    "deload": "no",
    "overview_and_execution": "Use ~3RM load. Perform 3 reps, rest 30s, then do sets of 2 reps until failure, then singles until failure. Increase weight 2.5–5 lbs once you reach ~10 total reps.",
    "example_application": "E.g., Bench Press at 225 lbs (3RM): 3 reps, rest 30s, 2 reps, rest 30s, 2 reps, rest 30s, then singles to failure. If you total ~10 reps, move to 230 lbs next session.",
    "important_notes": "Maintain strict form; heavy rest-pause can tax technique. Reduce load by 10% if you plateau.",
    "volume_metrics": "varies"
  }